<annotation>
	<folder>Damage Area 4</folder>
	<filename>2C8A0729.jpg</filename>
	<path>C:\Users\Vito\Documents\Lomba\2022 MZP\machine_learning\dataset\Damage Area 4\2C8A0729.jpg</path>
	<source>
		<database>Unknown</database>
	</source>
	<size>
		<width>8688</width>
		<height>5792</height>
		<depth>3</depth>
	</size>
	<segmented>0</segmented>
	<object>
		<name>DamageArea</name>
		<pose>Unspecified</pose>
		<truncated>0</truncated>
		<difficult>0</difficult>
		<bndbox>
			<xmin>4266</xmin>
			<ymin>2464</ymin>
			<xmax>4816</xmax>
			<ymax>3045</ymax>
		</bndbox>
	</object>
	<object>
		<name>DamageArea</name>
		<pose>Unspecified</pose>
		<truncated>0</truncated>
		<difficult>0</difficult>
		<bndbox>
			<xmin>3903</xmin>
			<ymin>2214</ymin>
			<xmax>4141</xmax>
			<ymax>2539</ymax>
		</bndbox>
	</object>
	<object>
		<name>DamageArea</name>
		<pose>Unspecified</pose>
		<truncated>1</truncated>
		<difficult>0</difficult>
		<bndbox>
			<xmin>3</xmin>
			<ymin>1</ymin>
			<xmax>1041</xmax>
			<ymax>1258</ymax>
		</bndbox>
	</object>
	<object>
		<name>DamageArea</name>
		<pose>Unspecified</pose>
		<truncated>0</truncated>
		<difficult>0</difficult>
		<bndbox>
			<xmin>1053</xmin>
			<ymin>89</ymin>
			<xmax>1772</xmax>
			<ymax>920</ymax>
		</bndbox>
	</object>
	<object>
		<name>DamageArea</name>
		<pose>Unspecified</pose>
		<truncated>0</truncated>
		<difficult>0</difficult>
		<bndbox>
			<xmin>1828</xmin>
			<ymin>720</ymin>
			<xmax>2241</xmax>
			<ymax>1195</ymax>
		</bndbox>
	</object>
	<object>
		<name>DamageArea</name>
		<pose>Unspecified</pose>
		<truncated>0</truncated>
		<difficult>0</difficult>
		<bndbox>
			<xmin>2272</xmin>
			<ymin>958</ymin>
			<xmax>2872</xmax>
			<ymax>1708</ymax>
		</bndbox>
	</object>
	<object>
		<name>DamageArea</name>
		<pose>Unspecified</pose>
		<truncated>0</truncated>
		<difficult>0</difficult>
		<bndbox>
			<xmin>2903</xmin>
			<ymin>1389</ymin>
			<xmax>3416</xmax>
			<ymax>1964</ymax>
		</bndbox>
	</object>
	<object>
		<name>DamageArea</name>
		<pose>Unspecified</pose>
		<truncated>0</truncated>
		<difficult>0</difficult>
		<bndbox>
			<xmin>3460</xmin>
			<ymin>1739</ymin>
			<xmax>3885</xmax>
			<ymax>2227</ymax>
		</bndbox>
	</object>
</annotation>
