<annotation>
	<folder>Edge Area</folder>
	<filename>2C8A0874.JPG</filename>
	<path>C:\Users\Vito\Documents\Lomba\2022 MZP\machine_learning\dataset\Edge Area\2C8A0874.JPG</path>
	<source>
		<database>Unknown</database>
	</source>
	<size>
		<width>8688</width>
		<height>5792</height>
		<depth>3</depth>
	</size>
	<segmented>0</segmented>
	<object>
		<name>DamageArea</name>
		<pose>Unspecified</pose>
		<truncated>0</truncated>
		<difficult>0</difficult>
		<bndbox>
			<xmin>41</xmin>
			<ymin>3177</ymin>
			<xmax>803</xmax>
			<ymax>3389</ymax>
		</bndbox>
	</object>
	<object>
		<name>DamageArea</name>
		<pose>Unspecified</pose>
		<truncated>1</truncated>
		<difficult>0</difficult>
		<bndbox>
			<xmin>41</xmin>
			<ymin>2245</ymin>
			<xmax>8688</xmax>
			<ymax>3239</ymax>
		</bndbox>
	</object>
</annotation>
