<annotation>
	<folder>Edge Area</folder>
	<filename>2C8A0873.JPG</filename>
	<path>C:\Users\Vito\Documents\Lomba\2022 MZP\machine_learning\dataset\Edge Area\2C8A0873.JPG</path>
	<source>
		<database>Unknown</database>
	</source>
	<size>
		<width>8688</width>
		<height>5792</height>
		<depth>3</depth>
	</size>
	<segmented>0</segmented>
	<object>
		<name>DamageArea</name>
		<pose>Unspecified</pose>
		<truncated>0</truncated>
		<difficult>0</difficult>
		<bndbox>
			<xmin>10</xmin>
			<ymin>2833</ymin>
			<xmax>1547</xmax>
			<ymax>5258</ymax>
		</bndbox>
	</object>
	<object>
		<name>DamageArea</name>
		<pose>Unspecified</pose>
		<truncated>0</truncated>
		<difficult>0</difficult>
		<bndbox>
			<xmin>1566</xmin>
			<ymin>2783</ymin>
			<xmax>3641</xmax>
			<ymax>4177</ymax>
		</bndbox>
	</object>
	<object>
		<name>DamageArea</name>
		<pose>Unspecified</pose>
		<truncated>0</truncated>
		<difficult>0</difficult>
		<bndbox>
			<xmin>3660</xmin>
			<ymin>2683</ymin>
			<xmax>4960</xmax>
			<ymax>3302</ymax>
		</bndbox>
	</object>
	<object>
		<name>DamageArea</name>
		<pose>Unspecified</pose>
		<truncated>1</truncated>
		<difficult>0</difficult>
		<bndbox>
			<xmin>4966</xmin>
			<ymin>2583</ymin>
			<xmax>8688</xmax>
			<ymax>3114</ymax>
		</bndbox>
	</object>
	<object>
		<name>DamageArea</name>
		<pose>Unspecified</pose>
		<truncated>0</truncated>
		<difficult>0</difficult>
		<bndbox>
			<xmin>5559</xmin>
			<ymin>3133</ymin>
			<xmax>6203</xmax>
			<ymax>3421</ymax>
		</bndbox>
	</object>
</annotation>
