<annotation>
	<folder>Reference Area 2</folder>
	<filename>2C8A0845.JPG</filename>
	<path>C:\Users\Vito\Documents\Lomba\2022 MZP\machine_learning\dataset\Reference Area 2\2C8A0845.JPG</path>
	<source>
		<database>Unknown</database>
	</source>
	<size>
		<width>8688</width>
		<height>5792</height>
		<depth>3</depth>
	</size>
	<segmented>0</segmented>
	<object>
		<name>ReferenceArea</name>
		<pose>Unspecified</pose>
		<truncated>0</truncated>
		<difficult>0</difficult>
		<bndbox>
			<xmin>3599</xmin>
			<ymin>2286</ymin>
			<xmax>4179</xmax>
			<ymax>3516</ymax>
		</bndbox>
	</object>
	<object>
		<name>ReferenceArea</name>
		<pose>Unspecified</pose>
		<truncated>0</truncated>
		<difficult>0</difficult>
		<bndbox>
			<xmin>4289</xmin>
			<ymin>2136</ymin>
			<xmax>4869</xmax>
			<ymax>3356</ymax>
		</bndbox>
	</object>
	<object>
		<name>ReferenceArea</name>
		<pose>Unspecified</pose>
		<truncated>0</truncated>
		<difficult>0</difficult>
		<bndbox>
			<xmin>4909</xmin>
			<ymin>2806</ymin>
			<xmax>5569</xmax>
			<ymax>3136</ymax>
		</bndbox>
	</object>
	<object>
		<name>ReferenceArea</name>
		<pose>Unspecified</pose>
		<truncated>0</truncated>
		<difficult>0</difficult>
		<bndbox>
			<xmin>3159</xmin>
			<ymin>2426</ymin>
			<xmax>3549</xmax>
			<ymax>2976</ymax>
		</bndbox>
	</object>
	<object>
		<name>ReferenceArea</name>
		<pose>Unspecified</pose>
		<truncated>0</truncated>
		<difficult>0</difficult>
		<bndbox>
			<xmin>4969</xmin>
			<ymin>2406</ymin>
			<xmax>5289</xmax>
			<ymax>2776</ymax>
		</bndbox>
	</object>
</annotation>
